LICENSE
MANIFEST.in
README.rst
setup.cfg
setup.py
kani_highcharts/__init__.py
kani_highcharts/ipynb.py
kani_highcharts/version.py
kani_highcharts.egg-info/PKG-INFO
kani_highcharts.egg-info/SOURCES.txt
kani_highcharts.egg-info/dependency_links.txt
kani_highcharts.egg-info/requires.txt
kani_highcharts.egg-info/top_level.txt
kani_highcharts/highcharts/__init__.py
kani_highcharts/highcharts/common.py
kani_highcharts/highcharts/highchart_types.py
kani_highcharts/highcharts/highcharts.py
kani_highcharts/highcharts/options.py
kani_highcharts/highcharts/templates/base.html
kani_highcharts/highcharts/templates/content.html
kani_highcharts/highcharts/templates/page.html
kani_highcharts/highcharts/templates/test.html
kani_highcharts/highmaps/__init__.py
kani_highcharts/highmaps/common.py
kani_highcharts/highmaps/highmap_helper.py
kani_highcharts/highmaps/highmap_types.py
kani_highcharts/highmaps/highmaps.py
kani_highcharts/highmaps/options.py
kani_highcharts/highmaps/templates/base.html
kani_highcharts/highmaps/templates/content.html
kani_highcharts/highmaps/templates/page.html
kani_highcharts/highmaps/templates/test.html
kani_highcharts/highstock/__init__.py
kani_highcharts/highstock/common.py
kani_highcharts/highstock/highstock.py
kani_highcharts/highstock/highstock_helper.py
kani_highcharts/highstock/highstock_types.py
kani_highcharts/highstock/options.py
kani_highcharts/highstock/templates/base.html
kani_highcharts/highstock/templates/content.html
kani_highcharts/highstock/templates/page.html
kani_highcharts/highstock/templates/test.html
tests/test_highmaps.py
tests/test_highstock.py
tests/test_kani_highcharts.py