Metadata-Version: 2.1
Name: kani-highcharts
Version: 0.1.4
Summary: Python Highcharts wrapper
Home-page: https://github.com/fx-kirin/kani_highcharts
Author: fx-kirin
Author-email: fx-kirin@gmail.com
Keywords: python,ipython,highcharts,chart,visualization,graph,javascript,html
Classifier: Framework :: IPython
Classifier: Intended Audience :: Developers
Classifier: Intended Audience :: Financial and Insurance Industry
Classifier: Intended Audience :: Science/Research
Classifier: License :: OSI Approved :: MIT License
Classifier: Programming Language :: Python
Classifier: Programming Language :: Python :: 3
License-File: LICENSE
